src/cmp/__init__.py
src/cmp/anomaly_detection_functions.py
src/cmp/data/.gitkeep
src/cmp/data/data.csv
src/cmp/data/group_cluster.csv
src/cmp/data/time_window_corrected.csv
src/cmp/main.py
src/cmp/results/.gitkeep
src/cmp/results/figures/.gitkeep
src/cmp/results/reports/.gitkeep
src/cmp/templates/.gitkeep
src/cmp/templates/cmp.html
src/cmp/utils.py
src/distancematrix/__init__.py
src/distancematrix/calculator.py
src/distancematrix/consumer/__init__.py
src/distancematrix/consumer/abstract_consumer.py
src/distancematrix/consumer/contextmanager.py
src/distancematrix/consumer/contextual_matrix_profile.py
src/distancematrix/consumer/distance_matrix.py
src/distancematrix/consumer/matrix_profile_lr.py
src/distancematrix/consumer/multidimensional_matrix_profile_lr.py
src/distancematrix/consumer/radius_profile.py
src/distancematrix/consumer/threshold_counter.py
src/distancematrix/generator/__init__.py
src/distancematrix/generator/abstract_generator.py
src/distancematrix/generator/euclidean.py
src/distancematrix/generator/filter_generator.py
src/distancematrix/generator/znorm_euclidean.py
src/distancematrix/insights.py
src/distancematrix/interrupt_util.py
src/distancematrix/math_tricks.py
src/distancematrix/ostinato.py
src/distancematrix/ringbuffer.py
src/distancematrix/tests/__init__.py
src/distancematrix/tests/consumer/__init__.py
src/distancematrix/tests/consumer/test_contextmanager.py
src/distancematrix/tests/consumer/test_contextual_matrix_profile.py
src/distancematrix/tests/consumer/test_distance_matrix.py
src/distancematrix/tests/consumer/test_matrix_profile_lr.py
src/distancematrix/tests/consumer/test_multidimensional_matrix_profile_lr.py
src/distancematrix/tests/consumer/test_radius_profile.py
src/distancematrix/tests/consumer/test_threshold_counter.py
src/distancematrix/tests/generator/__init__.py
src/distancematrix/tests/generator/mock_generator.py
src/distancematrix/tests/generator/test_euclidean.py
src/distancematrix/tests/generator/test_filter_generator.py
moderate_matrix_profile-1.0.1.dist-info/LICENSE.md
moderate_matrix_profile-1.0.1.dist-info/METADATA
moderate_matrix_profile-1.0.1.dist-info/WHEEL
moderate_matrix_profile-1.0.1.dist-info/RECORD
