Metadata-Version: 2.1
Name: moderate-matrix-profile
Version: 1.0.1
Summary: Contextual matrix profile for anomaly detection in building electrical loads
Author: RobertoChiosa
Author-email: roberto.chiosa@polito.it
Requires-Python: >=3.11,<4.0
Classifier: Programming Language :: Python :: 3
Classifier: Programming Language :: Python :: 3.11
Classifier: Programming Language :: Python :: 3.12
Requires-Dist: argparse (>=1.4.0,<2.0.0)
Requires-Dist: jinja2 (>=3.1.4,<4.0.0)
Requires-Dist: kneed (>=0.8.5,<0.9.0)
Requires-Dist: logger (>=1.4,<2.0)
Requires-Dist: matplotlib (>=3.9.1,<4.0.0)
Requires-Dist: numpy (>=2.0.0,<3.0.0)
Requires-Dist: pandas (>=2.2.2,<3.0.0)
Requires-Dist: plotly (>=5.22.0,<6.0.0)
Requires-Dist: requests (>=2.32.3,<3.0.0)
Requires-Dist: scipy (>=1.14.0,<2.0.0)
Requires-Dist: seaborn (>=0.13.2,<0.14.0)
